sdom/__init__.py
sdom/__main__.py
sdom/config_sdom.py
sdom/constants.py
sdom/initializations.py
sdom/io_manager.py
sdom/optimization_main.py
sdom/common/utilities.py
sdom/models/formulations_hydro.py
sdom/models/formulations_imports_exports.py
sdom/models/formulations_load.py
sdom/models/formulations_nuclear.py
sdom/models/formulations_other_renewables.py
sdom/models/formulations_resiliency.py
sdom/models/formulations_storage.py
sdom/models/formulations_system.py
sdom/models/formulations_thermal.py
sdom/models/formulations_vre.py
sdom/models/models_utils.py
sdom-0.0.8.dist-info/METADATA
sdom-0.0.8.dist-info/WHEEL
sdom-0.0.8.dist-info/RECORD
