Metadata-Version: 2.4
Name: sdom
Version: 0.0.8
Summary: A Python package for NREL open-source SDOM (Storage Deployment Optimization Model)
Project-URL: Homepage, https://github.com/Omar0902/SDOM
Project-URL: Repository, https://github.com/Omar0902/SDOM
Project-URL: Issues, https://github.com/Omar0902/SDOM/issues
Author-email: Omar Jose Guerra Fernandez <OmarJose.GuerraFernandez@nrel.gov>, Mariya Koleva <Mariya.Koleva@nrel.gov>, Sebastian de Jesus Manrique Machado <SebastiandeJesus.Machado@nrel.gov>
Maintainer-email: Omar Jose Guerra Fernandez <OmarJose.GuerraFernandez@nrel.gov>, Mariya Koleva <Mariya.Koleva@nrel.gov>, Sebastian de Jesus Manrique Machado <SebastiandeJesus.Machado@nrel.gov>, Pedro Andres Sanchez Perez <pedroandres.sanchezperez@nrel.gov>
License: MIT
Classifier: License :: OSI Approved :: MIT License
Classifier: Operating System :: OS Independent
Classifier: Programming Language :: Python :: 3
Requires-Python: >=3.10
Requires-Dist: numpy>2.2
Requires-Dist: pandas>2.2
Requires-Dist: pyomo>6.9
